polybeat/__init__.py
polybeat/sounds/kick_drum.wav
polybeat/sounds/low_bongo.wav
polybeat/sounds/open_conga.wav
polybeat/sounds/side_stick.wav
polybeat-1.1.0.dist-info/METADATA
polybeat-1.1.0.dist-info/WHEEL
polybeat-1.1.0.dist-info/top_level.txt
polybeat-1.1.0.dist-info/RECORD
