Metadata-Version: 2.1
Name: polybeat
Version: 1.1.0
Summary: A toy for visualizing polyrhythms
Home-page: https://github.com/chunribu/polybeat/
Author: Jian Jiang
Author-email: pccfreespace@gmail.com
License: MIT
Keywords: polybeat polyrhythm pccfs
Classifier: Operating System :: POSIX :: Linux
Classifier: Operating System :: MacOS :: MacOS X
Classifier: Operating System :: Microsoft :: Windows
Classifier: Programming Language :: Python :: 3
Classifier: License :: OSI Approved :: MIT License
